{
  "Route_0": {
    "Path": [
      "d1_4",
      "l4_cp1_241",
      "d1_4"
    ],
    "Cost": 951.8399999999999,
    "Data": {
      "total_dh_dist": 28.8,
      "total_dh_time": 86.39999999999999,
      "total_travel_dist": 24.0,
      "total_travel_time": 71.0,
      "total_wait_time": 0,
      "final_time": "2025-09-07 21:56:24",
      "total_charging_time": 0
    }
  },
  "Route_1": {
    "Path": [
      "d2_4",
      "l4_cp2_276",
      "d2_4"
    ],
    "Cost": 934.24,
    "Data": {
      "total_dh_dist": 28.8,
      "total_dh_time": 86.39999999999999,
      "total_travel_dist": 24.0,
      "total_travel_time": 60.0,
      "total_wait_time": 0,
      "final_time": "2025-09-08 00:00:24",
      "total_charging_time": 0
    }
  },
  "Route_2": {
    "Path": [
      "d2_4",
      "l4_cp2_148",
      "d2_4"
    ],
    "Cost": 947.04,
    "Data": {
      "total_dh_dist": 28.8,
      "total_dh_time": 86.39999999999999,
      "total_travel_dist": 24.0,
      "total_travel_time": 68.0,
      "total_wait_time": 0,
      "final_time": "2025-09-07 16:26:24",
      "total_charging_time": 0
    }
  },
  "Route_3": {
    "Path": [
      "d2_4",
      "l4_cp2_278",
      "d2_4"
    ],
    "Cost": 934.24,
    "Data": {
      "total_dh_dist": 28.8,
      "total_dh_time": 86.39999999999999,
      "total_travel_dist": 24.0,
      "total_travel_time": 60.0,
      "total_wait_time": 0,
      "final_time": "2025-09-08 00:07:24",
      "total_charging_time": 0
    }
  },
  "Route_4": {
    "Path": [
      "d2_4",
      "l4_cp2_152",
      "d2_4"
    ],
    "Cost": 950.24,
    "Data": {
      "total_dh_dist": 28.8,
      "total_dh_time": 86.39999999999999,
      "total_travel_dist": 24.0,
      "total_travel_time": 70.0,
      "total_wait_time": 0,
      "final_time": "2025-09-07 16:40:24",
      "total_charging_time": 0
    }
  },
  "Route_5": {
    "Path": [
      "d2_4",
      "l4_cp2_124",
      "d2_4"
    ],
    "Cost": 945.44,
    "Data": {
      "total_dh_dist": 28.8,
      "total_dh_time": 86.39999999999999,
      "total_travel_dist": 24.0,
      "total_travel_time": 67.0,
      "total_wait_time": 0,
      "final_time": "2025-09-07 15:07:24",
      "total_charging_time": 0
    }
  },
  "Route_6": {
    "Path": [
      "d1_4",
      "l4_cp1_167",
      "d1_4"
    ],
    "Cost": 950.24,
    "Data": {
      "total_dh_dist": 28.8,
      "total_dh_time": 86.39999999999999,
      "total_travel_dist": 24.0,
      "total_travel_time": 70.0,
      "total_wait_time": 0,
      "final_time": "2025-09-07 17:29:24",
      "total_charging_time": 0
    }
  },
  "Route_7": {
    "Path": [
      "d2_4",
      "l4_cp2_58",
      "d2_4"
    ],
    "Cost": 971.04,
    "Data": {
      "total_dh_dist": 28.8,
      "total_dh_time": 86.39999999999999,
      "total_travel_dist": 24.0,
      "total_travel_time": 83.0,
      "total_wait_time": 0,
      "final_time": "2025-09-07 11:44:24",
      "total_charging_time": 0
    }
  },
  "Route_8": {
    "Path": [
      "d2_4",
      "l4_cp2_156",
      "d2_4"
    ],
    "Cost": 950.24,
    "Data": {
      "total_dh_dist": 28.8,
      "total_dh_time": 86.39999999999999,
      "total_travel_dist": 24.0,
      "total_travel_time": 70.0,
      "total_wait_time": 0,
      "final_time": "2025-09-07 16:55:24",
      "total_charging_time": 0
    }
  },
  "Route_9": {
    "Path": [
      "d1_4",
      "l4_cp1_81",
      "d1_4"
    ],
    "Cost": 953.44,
    "Data": {
      "total_dh_dist": 28.8,
      "total_dh_time": 86.39999999999999,
      "total_travel_dist": 24.0,
      "total_travel_time": 72.0,
      "total_wait_time": 0,
      "final_time": "2025-09-07 12:46:24",
      "total_charging_time": 0
    }
  },
  "Route_10": {
    "Path": [
      "d1_4",
      "l4_cp1_191",
      "d1_4"
    ],
    "Cost": 959.8399999999999,
    "Data": {
      "total_dh_dist": 28.8,
      "total_dh_time": 86.39999999999999,
      "total_travel_dist": 24.0,
      "total_travel_time": 76.0,
      "total_wait_time": 0,
      "final_time": "2025-09-07 19:10:24",
      "total_charging_time": 0
    }
  },
  "Route_11": {
    "Path": [
      "d2_4",
      "l4_cp2_64",
      "d2_4"
    ],
    "Cost": 961.44,
    "Data": {
      "total_dh_dist": 28.8,
      "total_dh_time": 86.39999999999999,
      "total_travel_dist": 24.0,
      "total_travel_time": 77.0,
      "total_wait_time": 0,
      "final_time": "2025-09-07 11:58:24",
      "total_charging_time": 0
    }
  },
  "Route_12": {
    "Path": [
      "d1_4",
      "l4_cp1_207",
      "d1_4"
    ],
    "Cost": 961.44,
    "Data": {
      "total_dh_dist": 28.8,
      "total_dh_time": 86.39999999999999,
      "total_travel_dist": 24.0,
      "total_travel_time": 77.0,
      "total_wait_time": 0,
      "final_time": "2025-09-07 20:12:24",
      "total_charging_time": 0
    }
  },
  "Route_13": {
    "Path": [
      "d2_4",
      "l4_cp2_222",
      "d2_4"
    ],
    "Cost": 959.8399999999999,
    "Data": {
      "total_dh_dist": 28.8,
      "total_dh_time": 86.39999999999999,
      "total_travel_dist": 24.0,
      "total_travel_time": 76.0,
      "total_wait_time": 0,
      "final_time": "2025-09-07 20:57:24",
      "total_charging_time": 0
    }
  },
  "Route_14": {
    "Path": [
      "d1_4",
      "l4_cp1_31",
      "d1_4"
    ],
    "Cost": 975.8399999999999,
    "Data": {
      "total_dh_dist": 28.8,
      "total_dh_time": 86.39999999999999,
      "total_travel_dist": 24.0,
      "total_travel_time": 86.0,
      "total_wait_time": 0,
      "final_time": "2025-09-07 10:15:24",
      "total_charging_time": 0
    }
  },
  "Route_15": {
    "Path": [
      "d2_4",
      "l4_cp2_104",
      "d2_4"
    ],
    "Cost": 947.04,
    "Data": {
      "total_dh_dist": 28.8,
      "total_dh_time": 86.39999999999999,
      "total_travel_dist": 24.0,
      "total_travel_time": 68.0,
      "total_wait_time": 0,
      "final_time": "2025-09-07 14:02:24",
      "total_charging_time": 0
    }
  },
  "Route_16": {
    "Path": [
      "d1_59",
      "l4_cp2_142",
      "d1_59"
    ],
    "Cost": 906.72,
    "Data": {
      "total_dh_dist": 20.4,
      "total_dh_time": 61.2,
      "total_travel_dist": 24.0,
      "total_travel_time": 68.0,
      "total_wait_time": 0,
      "final_time": "2025-09-07 14:55:14.400000",
      "total_charging_time": 0
    }
  },
  "Route_17": {
    "Path": [
      "d1_4",
      "l4_cp1_253",
      "d1_4"
    ],
    "Cost": 943.8399999999999,
    "Data": {
      "total_dh_dist": 28.8,
      "total_dh_time": 86.39999999999999,
      "total_travel_dist": 24.0,
      "total_travel_time": 66.0,
      "total_wait_time": 0,
      "final_time": "2025-09-07 22:37:24",
      "total_charging_time": 0
    }
  },
  "Route_18": {
    "Path": [
      "d1_4",
      "l4_cp1_157",
      "d1_4"
    ],
    "Cost": 950.24,
    "Data": {
      "total_dh_dist": 28.8,
      "total_dh_time": 86.39999999999999,
      "total_travel_dist": 24.0,
      "total_travel_time": 70.0,
      "total_wait_time": 0,
      "final_time": "2025-09-07 16:59:24",
      "total_charging_time": 0
    }
  },
  "Route_19": {
    "Path": [
      "d1_59",
      "l4_cp2_230",
      "d1_59"
    ],
    "Cost": 919.52,
    "Data": {
      "total_dh_dist": 20.4,
      "total_dh_time": 61.2,
      "total_travel_dist": 24.0,
      "total_travel_time": 76.0,
      "total_wait_time": 0,
      "final_time": "2025-09-07 20:08:14.400000",
      "total_charging_time": 0
    }
  },
  "Route_20": {
    "Path": [
      "d1_4",
      "l4_cp1_229",
      "d1_4"
    ],
    "Cost": 959.8399999999999,
    "Data": {
      "total_dh_dist": 28.8,
      "total_dh_time": 86.39999999999999,
      "total_travel_dist": 24.0,
      "total_travel_time": 76.0,
      "total_wait_time": 0,
      "final_time": "2025-09-07 21:19:24",
      "total_charging_time": 0
    }
  },
  "Route_21": {
    "Path": [
      "d1_4",
      "l4_cp1_135",
      "d1_4"
    ],
    "Cost": 947.04,
    "Data": {
      "total_dh_dist": 28.8,
      "total_dh_time": 86.39999999999999,
      "total_travel_dist": 24.0,
      "total_travel_time": 68.0,
      "total_wait_time": 0,
      "final_time": "2025-09-07 15:43:24",
      "total_charging_time": 0
    }
  },
  "Route_22": {
    "Path": [
      "d1_4",
      "l4_cp1_133",
      "d1_4"
    ],
    "Cost": 947.04,
    "Data": {
      "total_dh_dist": 28.8,
      "total_dh_time": 86.39999999999999,
      "total_travel_dist": 24.0,
      "total_travel_time": 68.0,
      "total_wait_time": 0,
      "final_time": "2025-09-07 15:37:24",
      "total_charging_time": 0
    }
  },
  "Route_23": {
    "Path": [
      "d1_4",
      "l4_cp1_3",
      "d1_4"
    ],
    "Cost": 961.44,
    "Data": {
      "total_dh_dist": 28.8,
      "total_dh_time": 86.39999999999999,
      "total_travel_dist": 24.0,
      "total_travel_time": 77.0,
      "total_wait_time": 0,
      "final_time": "2025-09-07 08:40:24",
      "total_charging_time": 0
    }
  },
  "Route_24": {
    "Path": [
      "d1_59",
      "l4_cp2_176",
      "d1_59"
    ],
    "Cost": 914.72,
    "Data": {
      "total_dh_dist": 20.4,
      "total_dh_time": 61.2,
      "total_travel_dist": 24.0,
      "total_travel_time": 73.0,
      "total_wait_time": 0,
      "final_time": "2025-09-07 16:50:14.400000",
      "total_charging_time": 0
    }
  },
  "Route_25": {
    "Path": [
      "d1_4",
      "l4_cp1_147",
      "d1_4"
    ],
    "Cost": 947.04,
    "Data": {
      "total_dh_dist": 28.8,
      "total_dh_time": 86.39999999999999,
      "total_travel_dist": 24.0,
      "total_travel_time": 68.0,
      "total_wait_time": 0,
      "final_time": "2025-09-07 16:23:24",
      "total_charging_time": 0
    }
  },
  "Route_26": {
    "Path": [
      "d1_4",
      "l4_cp1_279",
      "d1_4"
    ],
    "Cost": 934.24,
    "Data": {
      "total_dh_dist": 28.8,
      "total_dh_time": 86.39999999999999,
      "total_travel_dist": 24.0,
      "total_travel_time": 60.0,
      "total_wait_time": 0,
      "final_time": "2025-09-08 00:10:24",
      "total_charging_time": 0
    }
  },
  "Route_27": {
    "Path": [
      "d1_4",
      "l4_cp1_131",
      "d1_4"
    ],
    "Cost": 945.44,
    "Data": {
      "total_dh_dist": 28.8,
      "total_dh_time": 86.39999999999999,
      "total_travel_dist": 24.0,
      "total_travel_time": 67.0,
      "total_wait_time": 0,
      "final_time": "2025-09-07 15:28:24",
      "total_charging_time": 0
    }
  },
  "Route_28": {
    "Path": [
      "d1_4",
      "l4_cp1_227",
      "l4_cp2_260",
      "d1_4"
    ],
    "Cost": 961.5,
    "Data": {
      "total_dh_dist": 0.0,
      "total_dh_time": 0.0,
      "total_travel_dist": 48.0,
      "total_travel_time": 142.0,
      "total_wait_time": 49.0,
      "final_time": "2025-09-07 21:41:00",
      "total_charging_time": 0
    }
  },
  "Route_29": {
    "Path": [
      "d2_4",
      "l59_cp2_52",
      "l59_cp1_55",
      "l59_cp2_72",
      "d2_4"
    ],
    "Cost": 1063.904,
    "Data": {
      "total_dh_dist": 21.48,
      "total_dh_time": 64.44,
      "total_travel_dist": 34.2,
      "total_travel_time": 100.0,
      "total_wait_time": 144.0,
      "final_time": "2025-09-07 18:31:31.200000",
      "total_charging_time": 0
    }
  },
  "Route_30": {
    "Path": [
      "d2_4",
      "l4_cp2_180",
      "d2_4"
    ],
    "Cost": 955.04,
    "Data": {
      "total_dh_dist": 28.8,
      "total_dh_time": 86.39999999999999,
      "total_travel_dist": 24.0,
      "total_travel_time": 73.0,
      "total_wait_time": 0,
      "final_time": "2025-09-07 18:24:24",
      "total_charging_time": 0
    }
  },
  "Route_31": {
    "Path": [
      "d1_4",
      "l4_cp1_127",
      "l4_cp2_160",
      "d1_4"
    ],
    "Cost": 944.4,
    "Data": {
      "total_dh_dist": 0.0,
      "total_dh_time": 0.0,
      "total_travel_dist": 48.0,
      "total_travel_time": 137.0,
      "total_wait_time": 36.0,
      "final_time": "2025-09-07 15:39:00",
      "total_charging_time": 0
    }
  },
  "Route_32": {
    "Path": [
      "d1_4",
      "l60_cp2_18",
      "l60_cp1_25",
      "l60_cp2_42",
      "d1_4"
    ],
    "Cost": 1063.336,
    "Data": {
      "total_dh_dist": 7.32,
      "total_dh_time": 21.96,
      "total_travel_dist": 57.0,
      "total_travel_time": 178.0,
      "total_wait_time": 62.0,
      "final_time": "2025-09-07 12:32:14.400000",
      "total_charging_time": 0
    }
  },
  "Route_33": {
    "Path": [
      "d2_4",
      "l4_cp2_8",
      "d2_4"
    ],
    "Cost": 969.44,
    "Data": {
      "total_dh_dist": 28.8,
      "total_dh_time": 86.39999999999999,
      "total_travel_dist": 24.0,
      "total_travel_time": 82.0,
      "total_wait_time": 0,
      "final_time": "2025-09-07 09:00:24",
      "total_charging_time": 0
    }
  },
  "Route_34": {
    "Path": [
      "d2_4",
      "l4_cp2_204",
      "d2_4"
    ],
    "Cost": 961.44,
    "Data": {
      "total_dh_dist": 28.8,
      "total_dh_time": 86.39999999999999,
      "total_travel_dist": 24.0,
      "total_travel_time": 77.0,
      "total_wait_time": 0,
      "final_time": "2025-09-07 19:58:24",
      "total_charging_time": 0
    }
  },
  "Route_35": {
    "Path": [
      "d1_4",
      "l4_cp1_245",
      "d1_4"
    ],
    "Cost": 951.8399999999999,
    "Data": {
      "total_dh_dist": 28.8,
      "total_dh_time": 86.39999999999999,
      "total_travel_dist": 24.0,
      "total_travel_time": 71.0,
      "total_wait_time": 0,
      "final_time": "2025-09-07 22:14:24",
      "total_charging_time": 0
    }
  },
  "Route_36": {
    "Path": [
      "d1_4",
      "l4_cp1_77",
      "d1_4"
    ],
    "Cost": 961.44,
    "Data": {
      "total_dh_dist": 28.8,
      "total_dh_time": 86.39999999999999,
      "total_travel_dist": 24.0,
      "total_travel_time": 77.0,
      "total_wait_time": 0,
      "final_time": "2025-09-07 12:42:24",
      "total_charging_time": 0
    }
  },
  "Route_37": {
    "Path": [
      "d1_4",
      "l4_cp1_159",
      "d1_4"
    ],
    "Cost": 950.24,
    "Data": {
      "total_dh_dist": 28.8,
      "total_dh_time": 86.39999999999999,
      "total_travel_dist": 24.0,
      "total_travel_time": 70.0,
      "total_wait_time": 0,
      "final_time": "2025-09-07 17:03:24",
      "total_charging_time": 0
    }
  },
  "Route_38": {
    "Path": [
      "d2_4",
      "l4_cp2_84",
      "d2_4"
    ],
    "Cost": 953.44,
    "Data": {
      "total_dh_dist": 28.8,
      "total_dh_time": 86.39999999999999,
      "total_travel_dist": 24.0,
      "total_travel_time": 72.0,
      "total_wait_time": 0,
      "final_time": "2025-09-07 12:56:24",
      "total_charging_time": 0
    }
  },
  "Route_39": {
    "Path": [
      "d2_60",
      "l60_cp2_38",
      "l60_cp1_79",
      "l60_cp2_100",
      "l60_cp1_113",
      "l60_cp2_120",
      "d2_60"
    ],
    "Cost": 1455.68,
    "Data": {
      "total_dh_dist": 6.6,
      "total_dh_time": 19.799999999999997,
      "total_travel_dist": 95.0,
      "total_travel_time": 260.0,
      "total_wait_time": 440.0,
      "final_time": "2025-09-07 23:02:48",
      "total_charging_time": 0
    }
  },
  "Route_40": {
    "Path": [
      "d1_4",
      "l4_cp1_79",
      "l4_cp2_186",
      "l4_cp1_223",
      "l60_cp2_102",
      "d1_4"
    ],
    "Cost": 1427.1246768485044,
    "Data": {
      "total_dh_dist": 7.317287721910654,
      "total_dh_time": 21.951863165731965,
      "total_travel_dist": 91.0,
      "total_travel_time": 274.0,
      "total_wait_time": 362.28813683333334,
      "final_time": "2025-09-07 21:02:14.400000",
      "total_charging_time": 0
    }
  },
  "Route_41": {
    "Path": [
      "d1_4",
      "l4_cp1_165",
      "l4_cp2_206",
      "d1_4"
    ],
    "Cost": 996.8,
    "Data": {
      "total_dh_dist": 0.0,
      "total_dh_time": 0.0,
      "total_travel_dist": 48.0,
      "total_travel_time": 147.0,
      "total_wait_time": 88.0,
      "final_time": "2025-09-07 18:43:00",
      "total_charging_time": 0
    }
  },
  "Route_42": {
    "Path": [
      "d2_4",
      "l60_cp1_57",
      "l60_cp2_70",
      "l60_cp1_87",
      "d2_4"
    ],
    "Cost": 1259.724,
    "Data": {
      "total_dh_dist": 38.879999999999995,
      "total_dh_time": 116.63999999999999,
      "total_travel_dist": 57.0,
      "total_travel_time": 168.0,
      "total_wait_time": 149.0,
      "final_time": "2025-09-07 20:12:07.200000",
      "total_charging_time": 0
    }
  },
  "Route_43": {
    "Path": [
      "d1_4",
      "l4_cp1_121",
      "d1_4"
    ],
    "Cost": 945.44,
    "Data": {
      "total_dh_dist": 28.8,
      "total_dh_time": 86.39999999999999,
      "total_travel_dist": 24.0,
      "total_travel_time": 67.0,
      "total_wait_time": 0,
      "final_time": "2025-09-07 15:00:24",
      "total_charging_time": 0
    }
  },
  "Route_44": {
    "Path": [
      "d1_4",
      "l60_cp2_8",
      "l60_cp1_27",
      "l60_cp2_46",
      "d1_4"
    ],
    "Cost": 1138.4360000000001,
    "Data": {
      "total_dh_dist": 7.32,
      "total_dh_time": 21.96,
      "total_travel_dist": 57.0,
      "total_travel_time": 179.0,
      "total_wait_time": 167.0,
      "final_time": "2025-09-07 13:04:14.400000",
      "total_charging_time": 0
    }
  },
  "Route_45": {
    "Path": [
      "d1_4",
      "l4_cp1_61",
      "l4_cp2_96",
      "d1_4"
    ],
    "Cost": 961.4,
    "Data": {
      "total_dh_dist": 0.0,
      "total_dh_time": 0.0,
      "total_travel_dist": 48.0,
      "total_travel_time": 145.0,
      "total_wait_time": 42.0,
      "final_time": "2025-09-07 12:08:00",
      "total_charging_time": 0
    }
  },
  "Route_46": {
    "Path": [
      "d1_4",
      "l4_cp1_91",
      "d1_4"
    ],
    "Cost": 953.44,
    "Data": {
      "total_dh_dist": 28.8,
      "total_dh_time": 86.39999999999999,
      "total_travel_dist": 24.0,
      "total_travel_time": 72.0,
      "total_wait_time": 0,
      "final_time": "2025-09-07 13:22:24",
      "total_charging_time": 0
    }
  },
  "Route_47": {
    "Path": [
      "d1_4",
      "l4_cp1_5",
      "l4_cp2_50",
      "d1_4"
    ],
    "Cost": 1013.0,
    "Data": {
      "total_dh_dist": 0.0,
      "total_dh_time": 0.0,
      "total_travel_dist": 48.0,
      "total_travel_time": 165.0,
      "total_wait_time": 70.0,
      "final_time": "2025-09-07 09:56:00",
      "total_charging_time": 0
    }
  },
  "Route_48": {
    "Path": [
      "d2_4",
      "l4_cp2_30",
      "d2_4"
    ],
    "Cost": 975.8399999999999,
    "Data": {
      "total_dh_dist": 28.8,
      "total_dh_time": 86.39999999999999,
      "total_travel_dist": 24.0,
      "total_travel_time": 86.0,
      "total_wait_time": 0,
      "final_time": "2025-09-07 10:13:24",
      "total_charging_time": 0
    }
  },
  "Route_49": {
    "Path": [
      "d2_4",
      "l60_cp1_15",
      "d2_4"
    ],
    "Cost": 995.424,
    "Data": {
      "total_dh_dist": 38.879999999999995,
      "total_dh_time": 116.63999999999999,
      "total_travel_dist": 19.0,
      "total_travel_time": 68.0,
      "total_wait_time": 0,
      "final_time": "2025-09-07 09:58:07.200000",
      "total_charging_time": 0
    }
  },
  "Route_50": {
    "Path": [
      "d2_4",
      "l4_cp2_40",
      "d2_4"
    ],
    "Cost": 975.8399999999999,
    "Data": {
      "total_dh_dist": 28.8,
      "total_dh_time": 86.39999999999999,
      "total_travel_dist": 24.0,
      "total_travel_time": 86.0,
      "total_wait_time": 0,
      "final_time": "2025-09-07 10:40:24",
      "total_charging_time": 0
    }
  },
  "Route_51": {
    "Path": [
      "d2_4",
      "l4_cp2_216",
      "d2_4"
    ],
    "Cost": 961.44,
    "Data": {
      "total_dh_dist": 28.8,
      "total_dh_time": 86.39999999999999,
      "total_travel_dist": 24.0,
      "total_travel_time": 77.0,
      "total_wait_time": 0,
      "final_time": "2025-09-07 20:37:24",
      "total_charging_time": 0
    }
  },
  "Route_52": {
    "Path": [
      "d1_4",
      "l4_cp1_37",
      "d1_4"
    ],
    "Cost": 975.8399999999999,
    "Data": {
      "total_dh_dist": 28.8,
      "total_dh_time": 86.39999999999999,
      "total_travel_dist": 24.0,
      "total_travel_time": 86.0,
      "total_wait_time": 0,
      "final_time": "2025-09-07 10:33:24",
      "total_charging_time": 0
    }
  },
  "Route_53": {
    "Path": [
      "d1_4",
      "l4_cp1_209",
      "d1_4"
    ],
    "Cost": 961.44,
    "Data": {
      "total_dh_dist": 28.8,
      "total_dh_time": 86.39999999999999,
      "total_travel_dist": 24.0,
      "total_travel_time": 77.0,
      "total_wait_time": 0,
      "final_time": "2025-09-07 20:16:24",
      "total_charging_time": 0
    }
  },
  "Route_54": {
    "Path": [
      "d2_4",
      "l60_cp1_9",
      "l60_cp2_72",
      "d2_4"
    ],
    "Cost": 1382.864,
    "Data": {
      "total_dh_dist": 31.68,
      "total_dh_time": 95.04,
      "total_travel_dist": 38.0,
      "total_travel_time": 127.0,
      "total_wait_time": 468.0,
      "final_time": "2025-09-07 17:53:31.200000",
      "total_charging_time": 0
    }
  },
  "Route_55": {
    "Path": [
      "d1_4",
      "l4_cp1_17",
      "l4_cp2_78",
      "d1_4"
    ],
    "Cost": 1032.5,
    "Data": {
      "total_dh_dist": 0.0,
      "total_dh_time": 0.0,
      "total_travel_dist": 48.0,
      "total_travel_time": 154.0,
      "total_wait_time": 123.0,
      "final_time": "2025-09-07 11:14:00",
      "total_charging_time": 0
    }
  },
  "Route_56": {
    "Path": [
      "d1_4",
      "l4_cp1_281",
      "d1_4"
    ],
    "Cost": 934.24,
    "Data": {
      "total_dh_dist": 28.8,
      "total_dh_time": 86.39999999999999,
      "total_travel_dist": 24.0,
      "total_travel_time": 60.0,
      "total_wait_time": 0,
      "final_time": "2025-09-08 00:18:24",
      "total_charging_time": 0
    }
  },
  "Route_57": {
    "Path": [
      "d1_4",
      "l4_cp1_139",
      "l60_cp2_66",
      "l59_cp1_67",
      "l4_cp1_205",
      "l60_cp2_94",
      "l59_cp1_93",
      "d1_4"
    ],
    "Cost": 1418.1126847237751,
    "Data": {
      "total_dh_dist": 24.783957307730923,
      "total_dh_time": 74.35187192319276,
      "total_travel_dist": 108.80000000000001,
      "total_travel_time": 322.0,
      "total_wait_time": 119.92812806666666,
      "final_time": "2025-09-07 22:04:16.800000",
      "total_charging_time": 0
    }
  },
  "Route_58": {
    "Path": [
      "d2_4",
      "l4_cp2_234",
      "d2_4"
    ],
    "Cost": 959.8399999999999,
    "Data": {
      "total_dh_dist": 28.8,
      "total_dh_time": 86.39999999999999,
      "total_travel_dist": 24.0,
      "total_travel_time": 76.0,
      "total_wait_time": 0,
      "final_time": "2025-09-07 21:32:24",
      "total_charging_time": 0
    }
  },
  "Route_59": {
    "Path": [
      "d1_59",
      "l4_cp2_70",
      "d1_59"
    ],
    "Cost": 921.12,
    "Data": {
      "total_dh_dist": 20.4,
      "total_dh_time": 61.2,
      "total_travel_dist": 24.0,
      "total_travel_time": 77.0,
      "total_wait_time": 0,
      "final_time": "2025-09-07 11:11:14.400000",
      "total_charging_time": 0
    }
  },
  "Route_60": {
    "Path": [
      "d1_4",
      "l4_cp1_219",
      "d1_4"
    ],
    "Cost": 959.8399999999999,
    "Data": {
      "total_dh_dist": 28.8,
      "total_dh_time": 86.39999999999999,
      "total_travel_dist": 24.0,
      "total_travel_time": 76.0,
      "total_wait_time": 0,
      "final_time": "2025-09-07 20:44:24",
      "total_charging_time": 0
    }
  },
  "Route_61": {
    "Path": [
      "d1_59",
      "l4_cp2_264",
      "d1_59"
    ],
    "Cost": 903.52,
    "Data": {
      "total_dh_dist": 20.4,
      "total_dh_time": 61.2,
      "total_travel_dist": 24.0,
      "total_travel_time": 66.0,
      "total_wait_time": 0,
      "final_time": "2025-09-07 22:08:14.400000",
      "total_charging_time": 0
    }
  },
  "Route_62": {
    "Path": [
      "d1_59",
      "l59_cp1_95",
      "l4_cp1_287",
      "d1_59"
    ],
    "Cost": 961.0193310267662,
    "Data": {
      "total_dh_dist": 19.869381863909613,
      "total_dh_time": 59.60814559172884,
      "total_travel_dist": 35.4,
      "total_travel_time": 85.0,
      "total_wait_time": 42.3518544,
      "final_time": "2025-09-08 00:03:57.600000",
      "total_charging_time": 0
    }
  },
  "Route_63": {
    "Path": [
      "d2_59",
      "l60_cp1_25",
      "l60_cp2_106",
      "d2_59"
    ],
    "Cost": 1414.028,
    "Data": {
      "total_dh_dist": 27.36,
      "total_dh_time": 82.08,
      "total_travel_dist": 38.0,
      "total_travel_time": 110.0,
      "total_wait_time": 581.0,
      "final_time": "2025-09-07 21:51:02.400000",
      "total_charging_time": 0
    }
  },
  "Route_64": {
    "Path": [
      "d2_59",
      "l60_cp1_49",
      "l60_cp2_104",
      "d2_59"
    ],
    "Cost": 1279.9279999999999,
    "Data": {
      "total_dh_dist": 27.36,
      "total_dh_time": 82.08,
      "total_travel_dist": 38.0,
      "total_travel_time": 101.0,
      "total_wait_time": 410.0,
      "final_time": "2025-09-07 21:37:02.400000",
      "total_charging_time": 0
    }
  },
  "Route_65": {
    "Path": [
      "d1_59",
      "l59_cp1_25",
      "l59_cp2_34",
      "l60_cp1_39",
      "l60_cp2_52",
      "d1_59"
    ],
    "Cost": 1087.5,
    "Data": {
      "total_dh_dist": 0.0,
      "total_dh_time": 0.0,
      "total_travel_dist": 60.8,
      "total_travel_time": 177.0,
      "total_wait_time": 149.0,
      "final_time": "2025-09-07 14:09:00",
      "total_charging_time": 0
    }
  },
  "Route_66": {
    "Path": [
      "d1_59",
      "l4_cp2_34",
      "d1_59"
    ],
    "Cost": 935.52,
    "Data": {
      "total_dh_dist": 20.4,
      "total_dh_time": 61.2,
      "total_travel_dist": 24.0,
      "total_travel_time": 86.0,
      "total_wait_time": 0,
      "final_time": "2025-09-07 09:10:14.400000",
      "total_charging_time": 0
    }
  },
  "Route_67": {
    "Path": [
      "d1_4",
      "l4_cp1_195",
      "l60_cp2_90",
      "l59_cp1_87",
      "l4_cp1_265",
      "d1_4"
    ],
    "Cost": 1284.9640078752705,
    "Data": {
      "total_dh_dist": 35.58666958582027,
      "total_dh_time": 106.7600087574608,
      "total_travel_dist": 78.4,
      "total_travel_time": 231.0,
      "total_wait_time": 63.63999123333333,
      "final_time": "2025-09-07 23:24:24",
      "total_charging_time": 0
    }
  },
  "Route_68": {
    "Path": [
      "d2_4",
      "l4_cp2_272",
      "d2_4"
    ],
    "Cost": 934.24,
    "Data": {
      "total_dh_dist": 28.8,
      "total_dh_time": 86.39999999999999,
      "total_travel_dist": 24.0,
      "total_travel_time": 60.0,
      "total_wait_time": 0,
      "final_time": "2025-09-07 23:41:24",
      "total_charging_time": 0
    }
  },
  "Route_69": {
    "Path": [
      "d2_4",
      "l59_cp2_76",
      "l60_cp1_89",
      "l4_cp2_250",
      "d2_4"
    ],
    "Cost": 1171.1526768485046,
    "Data": {
      "total_dh_dist": 37.67728772191066,
      "total_dh_time": 113.03186316573195,
      "total_travel_dist": 54.4,
      "total_travel_time": 166.0,
      "total_wait_time": 35.28813683333333,
      "final_time": "2025-09-07 22:30:24",
      "total_charging_time": 0
    }
  },
  "Route_70": {
    "Path": [
      "d2_4",
      "l4_cp2_184",
      "d2_4"
    ],
    "Cost": 959.8399999999999,
    "Data": {
      "total_dh_dist": 28.8,
      "total_dh_time": 86.39999999999999,
      "total_travel_dist": 24.0,
      "total_travel_time": 76.0,
      "total_wait_time": 0,
      "final_time": "2025-09-07 18:47:24",
      "total_charging_time": 0
    }
  },
  "Route_71": {
    "Path": [
      "d2_4",
      "l4_cp2_154",
      "d2_4"
    ],
    "Cost": 950.24,
    "Data": {
      "total_dh_dist": 28.8,
      "total_dh_time": 86.39999999999999,
      "total_travel_dist": 24.0,
      "total_travel_time": 70.0,
      "total_wait_time": 0,
      "final_time": "2025-09-07 16:50:24",
      "total_charging_time": 0
    }
  },
  "Route_72": {
    "Path": [
      "d1_4",
      "l4_cp1_107",
      "d1_4"
    ],
    "Cost": 947.04,
    "Data": {
      "total_dh_dist": 28.8,
      "total_dh_time": 86.39999999999999,
      "total_travel_dist": 24.0,
      "total_travel_time": 68.0,
      "total_wait_time": 0,
      "final_time": "2025-09-07 14:12:24",
      "total_charging_time": 0
    }
  },
  "Route_73": {
    "Path": [
      "d2_4",
      "l4_cp2_12",
      "l59_cp1_23",
      "l4_cp1_111",
      "d2_4"
    ],
    "Cost": 1184.624729797071,
    "Data": {
      "total_dh_dist": 12.972122150778691,
      "total_dh_time": 38.91636645233608,
      "total_travel_dist": 59.4,
      "total_travel_time": 190.0,
      "total_wait_time": 169.0836335333333,
      "final_time": "2025-09-07 13:00:00",
      "total_charging_time": 0
    }
  },
  "Route_74": {
    "Path": [
      "d2_4",
      "l4_cp2_112",
      "d2_4"
    ],
    "Cost": 947.04,
    "Data": {
      "total_dh_dist": 28.8,
      "total_dh_time": 86.39999999999999,
      "total_travel_dist": 24.0,
      "total_travel_time": 68.0,
      "total_wait_time": 0,
      "final_time": "2025-09-07 14:30:24",
      "total_charging_time": 0
    }
  },
  "Route_75": {
    "Path": [
      "d2_60",
      "l60_cp2_6",
      "l4_cp1_145",
      "d2_60"
    ],
    "Cost": 1288.033398770305,
    "Data": {
      "total_dh_dist": 32.46274028686908,
      "total_dh_time": 97.38822086060722,
      "total_travel_dist": 43.0,
      "total_travel_time": 132.0,
      "total_wait_time": 315.73177913333336,
      "final_time": "2025-09-07 16:01:07.200000",
      "total_charging_time": 0
    }
  },
  "Route_76": {
    "Path": [
      "d1_59",
      "l4_cp2_158",
      "d1_59"
    ],
    "Cost": 909.9200000000001,
    "Data": {
      "total_dh_dist": 20.4,
      "total_dh_time": 61.2,
      "total_travel_dist": 24.0,
      "total_travel_time": 70.0,
      "total_wait_time": 0,
      "final_time": "2025-09-07 15:47:14.400000",
      "total_charging_time": 0
    }
  },
  "Route_77": {
    "Path": [
      "d1_59",
      "l59_cp2_6",
      "l4_cp1_171",
      "d1_59"
    ],
    "Cost": 1383.041398770305,
    "Data": {
      "total_dh_dist": 39.42274028686908,
      "total_dh_time": 118.26822086060724,
      "total_travel_dist": 35.4,
      "total_travel_time": 111.0,
      "total_wait_time": 451.73177913333336,
      "final_time": "2025-09-07 17:09:57.600000",
      "total_charging_time": 0
    }
  },
  "Route_78": {
    "Path": [
      "d1_59",
      "l59_cp1_3",
      "l4_cp1_183",
      "d1_59"
    ],
    "Cost": 1359.5193310267662,
    "Data": {
      "total_dh_dist": 19.869381863909613,
      "total_dh_time": 59.60814559172884,
      "total_travel_dist": 35.4,
      "total_travel_time": 114.0,
      "total_wait_time": 545.3518544,
      "final_time": "2025-09-07 18:04:57.600000",
      "total_charging_time": 0
    }
  },
  "Route_79": {
    "Path": [
      "d2_59",
      "l59_cp2_40",
      "l59_cp1_51",
      "l59_cp2_84",
      "l59_cp1_89",
      "d2_59"
    ],
    "Cost": 1208.0,
    "Data": {
      "total_dh_dist": 0.0,
      "total_dh_time": 0.0,
      "total_travel_dist": 45.6,
      "total_travel_time": 125.0,
      "total_wait_time": 440.0,
      "final_time": "2025-09-07 20:43:00",
      "total_charging_time": 0
    }
  },
  "Route_80": {
    "Path": [
      "d2_60",
      "l60_cp2_78",
      "l60_cp1_95",
      "d2_60"
    ],
    "Cost": 942.1,
    "Data": {
      "total_dh_dist": 0.0,
      "total_dh_time": 0.0,
      "total_travel_dist": 38.0,
      "total_travel_time": 115.0,
      "total_wait_time": 83.0,
      "final_time": "2025-09-07 20:18:00",
      "total_charging_time": 0
    }
  },
  "Route_81": {
    "Path": [
      "d1_59",
      "l59_cp1_73",
      "l4_cp1_233",
      "d1_59"
    ],
    "Cost": 1009.1193310267661,
    "Data": {
      "total_dh_dist": 19.869381863909613,
      "total_dh_time": 59.60814559172884,
      "total_travel_dist": 35.4,
      "total_travel_time": 112.0,
      "total_wait_time": 49.3518544,
      "final_time": "2025-09-07 20:51:57.600000",
      "total_charging_time": 0
    }
  },
  "Route_82": {
    "Path": [
      "d2_60",
      "l60_cp2_22",
      "l60_cp1_53",
      "l60_cp2_62",
      "d2_60"
    ],
    "Cost": 1143.58,
    "Data": {
      "total_dh_dist": 6.6,
      "total_dh_time": 19.799999999999997,
      "total_travel_dist": 57.0,
      "total_travel_time": 166.0,
      "total_wait_time": 209.0,
      "final_time": "2025-09-07 15:34:48",
      "total_charging_time": 0
    }
  },
  "Route_83": {
    "Path": [
      "d1_4",
      "l4_cp1_89",
      "l4_cp2_144",
      "d1_4"
    ],
    "Cost": 1002.4,
    "Data": {
      "total_dh_dist": 0.0,
      "total_dh_time": 0.0,
      "total_travel_dist": 48.0,
      "total_travel_time": 140.0,
      "total_wait_time": 112.0,
      "final_time": "2025-09-07 14:50:00",
      "total_charging_time": 0
    }
  },
  "Route_84": {
    "Path": [
      "d1_4",
      "l4_cp1_25",
      "l4_cp2_86",
      "d1_4"
    ],
    "Cost": 1031.9,
    "Data": {
      "total_dh_dist": 0.0,
      "total_dh_time": 0.0,
      "total_travel_dist": 48.0,
      "total_travel_time": 158.0,
      "total_wait_time": 113.0,
      "final_time": "2025-09-07 11:35:00",
      "total_charging_time": 0
    }
  },
  "Route_85": {
    "Path": [
      "d1_4",
      "l4_cp1_123",
      "l59_cp2_68",
      "l60_cp1_85",
      "l4_cp2_242",
      "d1_4"
    ],
    "Cost": 1266.8501373621527,
    "Data": {
      "total_dh_dist": 7.314865691767938,
      "total_dh_time": 21.94459707530381,
      "total_travel_dist": 78.4,
      "total_travel_time": 233.0,
      "total_wait_time": 227.05540291666665,
      "final_time": "2025-09-07 20:33:00",
      "total_charging_time": 0
    }
  },
  "Route_86": {
    "Path": [
      "d2_4",
      "l4_cp2_110",
      "d2_4"
    ],
    "Cost": 947.04,
    "Data": {
      "total_dh_dist": 28.8,
      "total_dh_time": 86.39999999999999,
      "total_travel_dist": 24.0,
      "total_travel_time": 68.0,
      "total_wait_time": 0,
      "final_time": "2025-09-07 14:23:24",
      "total_charging_time": 0
    }
  },
  "Route_87": {
    "Path": [
      "d1_59",
      "l59_cp1_11",
      "l4_cp1_51",
      "d1_59"
    ],
    "Cost": 1014.3193310267661,
    "Data": {
      "total_dh_dist": 19.869381863909613,
      "total_dh_time": 59.60814559172884,
      "total_travel_dist": 35.4,
      "total_travel_time": 124.0,
      "total_wait_time": 29.351854399999997,
      "final_time": "2025-09-07 10:46:57.600000",
      "total_charging_time": 0
    }
  },
  "Route_88": {
    "Path": [
      "d1_4",
      "l4_cp1_45",
      "d1_4"
    ],
    "Cost": 971.04,
    "Data": {
      "total_dh_dist": 28.8,
      "total_dh_time": 86.39999999999999,
      "total_travel_dist": 24.0,
      "total_travel_time": 83.0,
      "total_wait_time": 0,
      "final_time": "2025-09-07 11:04:24",
      "total_charging_time": 0
    }
  },
  "Route_89": {
    "Path": [
      "d1_4",
      "l4_cp1_105",
      "d1_4"
    ],
    "Cost": 947.04,
    "Data": {
      "total_dh_dist": 28.8,
      "total_dh_time": 86.39999999999999,
      "total_travel_dist": 24.0,
      "total_travel_time": 68.0,
      "total_wait_time": 0,
      "final_time": "2025-09-07 14:07:24",
      "total_charging_time": 0
    }
  },
  "Route_90": {
    "Path": [
      "d2_60",
      "l60_cp2_48",
      "l60_cp1_59",
      "l60_cp2_66",
      "l60_cp1_75",
      "d2_60"
    ],
    "Cost": 1128.1,
    "Data": {
      "total_dh_dist": 0.0,
      "total_dh_time": 0.0,
      "total_travel_dist": 76.0,
      "total_travel_time": 219.0,
      "total_wait_time": 111.0,
      "final_time": "2025-09-07 17:43:00",
      "total_charging_time": 0
    }
  },
  "Route_91": {
    "Path": [
      "d1_4",
      "l4_cp1_1",
      "l4_cp2_28",
      "l4_cp1_55",
      "l4_cp2_82",
      "l4_cp1_103",
      "c2_4",
      "l4_cp2_182",
      "l4_cp1_203",
      "l4_cp2_228",
      "l4_cp1_249",
      "d1_4"
    ],
    "Cost": 1985.836,
    "Data": {
      "total_dh_dist": 28.8,
      "total_dh_time": 86.39999999999999,
      "total_travel_dist": 216.0,
      "total_travel_time": 683.0,
      "total_wait_time": 229.0,
      "final_time": "2025-09-07 22:27:24",
      "total_charging_time": 200.72
    }
  },
  "Route_92": {
    "Path": [
      "d2_4",
      "l4_cp2_2",
      "l4_cp1_27",
      "l4_cp2_54",
      "l4_cp1_83",
      "l4_cp2_106",
      "c1_4",
      "l4_cp1_185",
      "l4_cp2_208",
      "l4_cp1_235",
      "l4_cp2_256",
      "d2_4"
    ],
    "Cost": 1994.536,
    "Data": {
      "total_dh_dist": 28.8,
      "total_dh_time": 86.39999999999999,
      "total_travel_dist": 216.0,
      "total_travel_time": 681.0,
      "total_wait_time": 246.0,
      "final_time": "2025-09-07 22:45:24",
      "total_charging_time": 200.72
    }
  },
  "Route_93": {
    "Path": [
      "d2_4",
      "l4_cp2_4",
      "l4_cp1_29",
      "l4_cp2_56",
      "l4_cp1_85",
      "l59_cp2_44",
      "c1_59",
      "l60_cp1_69",
      "l60_cp2_76",
      "l59_cp1_77",
      "l4_cp1_231",
      "l4_cp2_254",
      "d2_4"
    ],
    "Cost": 1980.844076397081,
    "Data": {
      "total_dh_dist": 36.426959833766894,
      "total_dh_time": 109.28087950130069,
      "total_travel_dist": 204.8,
      "total_travel_time": 643.0,
      "total_wait_time": 248.1191204829774,
      "final_time": "2025-09-07 22:39:24",
      "total_charging_time": 187.84102163297737
    }
  },
  "Route_94": {
    "Path": [
      "d1_59",
      "l59_cp1_1",
      "l59_cp2_8",
      "l59_cp1_13",
      "l59_cp2_22",
      "l59_cp1_29",
      "l59_cp2_32",
      "l4_cp1_97",
      "c2_4",
      "l4_cp2_170",
      "l4_cp1_189",
      "l4_cp2_212",
      "l4_cp1_237",
      "l60_cp2_108",
      "d1_59"
    ],
    "Cost": 1870.8844432238095,
    "Data": {
      "total_dh_dist": 12.660028008779733,
      "total_dh_time": 37.9800840263392,
      "total_travel_dist": 207.4,
      "total_travel_time": 644.0,
      "total_wait_time": 233.01991596418245,
      "final_time": "2025-09-07 21:15:00",
      "total_charging_time": 169.13947484751577
    }
  },
  "Route_95": {
    "Path": [
      "d2_59",
      "l60_cp1_1",
      "l60_cp2_8",
      "l60_cp1_17",
      "l4_cp2_68",
      "c1_4",
      "l4_cp1_145",
      "l4_cp2_168",
      "l4_cp1_187",
      "l4_cp2_210",
      "l59_cp2_84",
      "d2_59"
    ],
    "Cost": 1881.9783296802707,
    "Data": {
      "total_dh_dist": 34.14666958582026,
      "total_dh_time": 102.44000875746079,
      "total_travel_dist": 188.4,
      "total_travel_time": 599.0,
      "total_wait_time": 204.63999122951395,
      "final_time": "2025-09-07 20:25:02.400000",
      "total_charging_time": 169.3909688461806
    }
  },
  "Route_96": {
    "Path": [
      "d2_4",
      "l4_cp2_6",
      "l4_cp1_35",
      "l4_cp2_62",
      "l59_cp2_36",
      "l60_cp1_39",
      "c2_60",
      "l60_cp2_66",
      "l59_cp1_65",
      "l59_cp2_70",
      "l59_cp1_75",
      "l59_cp2_78",
      "l60_cp1_91",
      "l60_cp2_100",
      "d2_4"
    ],
    "Cost": 1888.3194060367662,
    "Data": {
      "total_dh_dist": 19.389381863909612,
      "total_dh_time": 58.168145591728845,
      "total_travel_dist": 205.00000000000003,
      "total_travel_time": 642.0,
      "total_wait_time": 224.351854407699,
      "final_time": "2025-09-07 21:27:31.200000",
      "total_charging_time": 177.137035707699
    }
  },
  "Route_97": {
    "Path": [
      "d2_59",
      "l59_cp2_2",
      "l60_cp1_5",
      "l4_cp2_42",
      "l4_cp1_67",
      "l4_cp2_94",
      "c1_4",
      "l4_cp1_169",
      "l4_cp2_188",
      "l4_cp1_211",
      "l4_cp2_236",
      "l4_cp1_257",
      "d2_59"
    ],
    "Cost": 1922.2015586535047,
    "Data": {
      "total_dh_dist": 8.877287721910655,
      "total_dh_time": 26.63186316573196,
      "total_travel_dist": 222.4,
      "total_travel_time": 702.0,
      "total_wait_time": 209.28813682951395,
      "final_time": "2025-09-07 21:40:55.200000",
      "total_charging_time": 178.73016884618062
    }
  },
  "Route_98": {
    "Path": [
      "d1_4",
      "l4_cp1_7",
      "l4_cp2_36",
      "l4_cp1_63",
      "l4_cp2_88",
      "l4_cp1_111",
      "c2_4",
      "l4_cp2_190",
      "l4_cp1_213",
      "l4_cp2_238",
      "l4_cp1_259",
      "d1_4"
    ],
    "Cost": 1988.1,
    "Data": {
      "total_dh_dist": 28.8,
      "total_dh_time": 86.39999999999999,
      "total_travel_dist": 216.0,
      "total_travel_time": 675.0,
      "total_wait_time": 250.00000000000003,
      "final_time": "2025-09-07 22:57:24",
      "total_charging_time": 200.20000000000002
    }
  },
  "Route_99": {
    "Path": [
      "d1_59",
      "l59_cp1_3",
      "l4_cp1_21",
      "l4_cp2_46",
      "l4_cp1_73",
      "l4_cp2_100",
      "c1_4",
      "l4_cp1_177",
      "l4_cp2_198",
      "l4_cp1_221",
      "l4_cp2_244",
      "l4_cp1_263",
      "d1_59"
    ],
    "Cost": 1994.2714060367662,
    "Data": {
      "total_dh_dist": 19.869381863909613,
      "total_dh_time": 59.60814559172884,
      "total_travel_dist": 227.4,
      "total_travel_time": 710.0,
      "total_wait_time": 226.351854407699,
      "final_time": "2025-09-07 22:41:57.600000",
      "total_charging_time": 186.49703570769898
    }
  },
  "Route_100": {
    "Path": [
      "d2_59",
      "l59_cp2_4",
      "l59_cp1_9",
      "l59_cp2_14",
      "l4_cp1_57",
      "l60_cp2_34",
      "l60_cp1_41",
      "c2_60",
      "l4_cp2_178",
      "l4_cp1_197",
      "l4_cp2_220",
      "l4_cp1_243",
      "d2_59"
    ],
    "Cost": 1828.8580018773139,
    "Data": {
      "total_dh_dist": 21.537315730690388,
      "total_dh_time": 64.61194719207116,
      "total_travel_dist": 192.2,
      "total_travel_time": 604.0,
      "total_wait_time": 214.30805279369642,
      "final_time": "2025-09-07 20:56:55.200000",
      "total_charging_time": 179.9096436936964
    }
  },
  "Route_101": {
    "Path": [
      "d1_4",
      "l4_cp1_9",
      "l4_cp2_38",
      "l4_cp1_65",
      "l4_cp2_90",
      "l4_cp1_113",
      "c2_4",
      "l4_cp2_192",
      "l4_cp1_217",
      "l4_cp2_240",
      "l59_cp2_92",
      "l60_cp1_115",
      "d1_4"
    ],
    "Cost": 1897.2593310267662,
    "Data": {
      "total_dh_dist": 6.789381863909613,
      "total_dh_time": 20.36814559172884,
      "total_travel_dist": 222.4,
      "total_travel_time": 683.0,
      "total_wait_time": 252.3518544,
      "final_time": "2025-09-07 22:10:43.200000",
      "total_charging_time": 199.68
    }
  },
  "Route_102": {
    "Path": [
      "d2_4",
      "l4_cp2_10",
      "l4_cp1_39",
      "l4_cp2_66",
      "l4_cp1_93",
      "l4_cp2_114",
      "c1_4",
      "l4_cp1_193",
      "l4_cp2_218",
      "d2_4"
    ],
    "Cost": 1761.364,
    "Data": {
      "total_dh_dist": 28.8,
      "total_dh_time": 86.39999999999999,
      "total_travel_dist": 168.0,
      "total_travel_time": 537.0,
      "total_wait_time": 241.0,
      "final_time": "2025-09-07 20:41:24",
      "total_charging_time": 199.68
    }
  },
  "Route_103": {
    "Path": [
      "d2_59",
      "l60_cp1_3",
      "l60_cp2_14",
      "l60_cp1_21",
      "l60_cp2_30",
      "l59_cp1_39",
      "l59_cp2_42",
      "c1_59",
      "l59_cp1_63",
      "d2_59"
    ],
    "Cost": 1393.14544,
    "Data": {
      "total_dh_dist": 13.68,
      "total_dh_time": 41.04,
      "total_travel_dist": 110.20000000000002,
      "total_travel_time": 354.0,
      "total_wait_time": 224.99999999999994,
      "final_time": "2025-09-07 15:56:00",
      "total_charging_time": 187.74079999999995
    }
  },
  "Route_104": {
    "Path": [
      "d1_59",
      "l59_cp1_5",
      "l4_cp2_26",
      "l4_cp1_53",
      "l4_cp2_80",
      "l60_cp2_44",
      "c1_59",
      "l60_cp1_73",
      "l60_cp2_82",
      "l60_cp1_89",
      "l60_cp2_98",
      "l60_cp1_109",
      "l60_cp2_116",
      "d1_59"
    ],
    "Cost": 1894.4506204492961,
    "Data": {
      "total_dh_dist": 13.578744065478372,
      "total_dh_time": 40.73623219643512,
      "total_travel_dist": 216.4,
      "total_travel_time": 659.0,
      "total_wait_time": 250.26376779214627,
      "final_time": "2025-09-07 22:09:00",
      "total_charging_time": 193.30284074214626
    }
  },
  "Route_105": {
    "Path": [
      "d1_4",
      "l4_cp1_13",
      "l60_cp1_19",
      "l60_cp2_26",
      "l59_cp1_37",
      "d1_4"
    ],
    "Cost": 1235.551231688544,
    "Data": {
      "total_dh_dist": 29.538974699696656,
      "total_dh_time": 88.61692409908997,
      "total_travel_dist": 73.4,
      "total_travel_time": 241.0,
      "total_wait_time": 11.663075899999999,
      "final_time": "2025-09-07 12:05:16.800000",
      "total_charging_time": 0
    }
  },
  "Route_106": {
    "Path": [
      "d1_4",
      "l4_cp1_15",
      "l59_cp2_20",
      "l59_cp1_27",
      "l4_cp1_75",
      "l4_cp2_102",
      "c1_4",
      "l4_cp1_175",
      "l4_cp2_194",
      "d1_4"
    ],
    "Cost": 1524.7161514070813,
    "Data": {
      "total_dh_dist": 7.626959833766896,
      "total_dh_time": 22.88087950130069,
      "total_travel_dist": 142.8,
      "total_travel_time": 456.0,
      "total_wait_time": 205.11912049067635,
      "final_time": "2025-09-07 17:55:00",
      "total_charging_time": 171.53805734067637
    }
  },
  "Route_107": {
    "Path": [
      "d2_4",
      "l4_cp2_16",
      "l4_cp1_43",
      "d2_4"
    ],
    "Cost": 970.3,
    "Data": {
      "total_dh_dist": 0.0,
      "total_dh_time": 0.0,
      "total_travel_dist": 48.0,
      "total_travel_time": 165.0,
      "total_wait_time": 9.0,
      "final_time": "2025-09-07 09:28:00",
      "total_charging_time": 0
    }
  },
  "Route_108": {
    "Path": [
      "d1_59",
      "l59_cp1_7",
      "l4_cp1_33",
      "l4_cp2_60",
      "l4_cp1_87",
      "l4_cp2_108",
      "c1_4",
      "l59_cp2_66",
      "l60_cp2_86",
      "l59_cp1_83",
      "l4_cp1_247",
      "l4_cp2_266",
      "d1_59"
    ],
    "Cost": 1901.7997659997638,
    "Data": {
      "total_dh_dist": 32.45025592946468,
      "total_dh_time": 97.35076778839402,
      "total_travel_dist": 197.20000000000002,
      "total_travel_time": 614.0,
      "total_wait_time": 226.88923219103233,
      "final_time": "2025-09-07 22:13:14.400000",
      "total_charging_time": 185.977035707699
    }
  },
  "Route_109": {
    "Path": [
      "d2_4",
      "l4_cp2_18",
      "l59_cp1_25",
      "l4_cp1_69",
      "l59_cp1_43",
      "l59_cp2_46",
      "c1_59",
      "l60_cp1_71",
      "l4_cp2_200",
      "l4_cp1_223",
      "l4_cp2_246",
      "l4_cp1_267",
      "d2_4"
    ],
    "Cost": 1882.9604405757862,
    "Data": {
      "total_dh_dist": 30.988384572386003,
      "total_dh_time": 92.96515371715802,
      "total_travel_dist": 197.2,
      "total_travel_time": 607.0,
      "total_wait_time": 219.0348462700749,
      "final_time": "2025-09-07 22:04:00",
      "total_charging_time": 179.01171108674154
    }
  },
  "Route_110": {
    "Path": [
      "d1_4",
      "l4_cp1_19",
      "l4_cp2_44",
      "l4_cp1_71",
      "l4_cp2_98",
      "l4_cp1_119",
      "c2_4",
      "l4_cp2_196",
      "l59_cp1_81",
      "d1_4"
    ],
    "Cost": 1651.961398770305,
    "Data": {
      "total_dh_dist": 24.182740286869077,
      "total_dh_time": 72.54822086060724,
      "total_travel_dist": 155.4,
      "total_travel_time": 488.0,
      "total_wait_time": 224.73177913333333,
      "final_time": "2025-09-07 19:53:16.800000",
      "total_charging_time": 196.04
    }
  },
  "Route_111": {
    "Path": [
      "d2_4",
      "l4_cp2_20",
      "l4_cp1_47",
      "l4_cp2_74",
      "l4_cp1_101",
      "l4_cp2_122",
      "c1_4",
      "l4_cp1_199",
      "l4_cp2_224",
      "l59_cp2_86",
      "l59_cp1_91",
      "l59_cp2_96",
      "d2_4"
    ],
    "Cost": 1852.9873310267662,
    "Data": {
      "total_dh_dist": 19.389381863909612,
      "total_dh_time": 58.168145591728845,
      "total_travel_dist": 202.20000000000002,
      "total_travel_time": 619.0,
      "total_wait_time": 245.3518544,
      "final_time": "2025-09-07 22:14:31.200000",
      "total_charging_time": 196.04
    }
  },
  "Route_112": {
    "Path": [
      "d2_4",
      "l4_cp2_22",
      "l4_cp1_49",
      "l4_cp2_76",
      "d2_4"
    ],
    "Cost": 1235.24,
    "Data": {
      "total_dh_dist": 28.8,
      "total_dh_time": 86.39999999999999,
      "total_travel_dist": 72.0,
      "total_travel_time": 242.0,
      "total_wait_time": 14.0,
      "final_time": "2025-09-07 12:39:24",
      "total_charging_time": 0
    }
  },
  "Route_113": {
    "Path": [
      "d2_4",
      "l4_cp2_32",
      "l59_cp2_28",
      "l60_cp2_36",
      "l4_cp1_117",
      "c2_4",
      "l4_cp2_202",
      "l4_cp1_225",
      "l4_cp2_248",
      "l4_cp1_269",
      "l4_cp2_284",
      "d2_4"
    ],
    "Cost": 2016.3163258282032,
    "Data": {
      "total_dh_dist": 59.494232488514534,
      "total_dh_time": 178.4826974655436,
      "total_travel_dist": 198.4,
      "total_travel_time": 584.0,
      "total_wait_time": 262.917302515416,
      "final_time": "2025-09-08 00:30:24",
      "total_charging_time": 175.28300268208267
    }
  },
  "Route_114": {
    "Path": [
      "d2_60",
      "l60_cp2_12",
      "d2_60"
    ],
    "Cost": 840.48,
    "Data": {
      "total_dh_dist": 6.6,
      "total_dh_time": 19.799999999999997,
      "total_travel_dist": 19.0,
      "total_travel_time": 68.0,
      "total_wait_time": 0,
      "final_time": "2025-09-07 08:52:48",
      "total_charging_time": 0
    }
  },
  "Route_115": {
    "Path": [
      "d2_59",
      "l59_cp2_12",
      "l59_cp1_21",
      "l60_cp2_24",
      "l59_cp1_35",
      "l59_cp2_38",
      "l60_cp1_43",
      "l4_cp2_126",
      "c1_4",
      "l4_cp1_201",
      "l4_cp2_226",
      "l59_cp2_88",
      "l60_cp2_118",
      "d2_59"
    ],
    "Cost": 1877.3007889900282,
    "Data": {
      "total_dh_dist": 44.8642783052142,
      "total_dh_time": 134.59283491564258,
      "total_travel_dist": 186.0,
      "total_travel_time": 552.0,
      "total_wait_time": 246.4471650715672,
      "final_time": "2025-09-07 23:02:02.400000",
      "total_charging_time": 183.9439463215672
    }
  },
  "Route_116": {
    "Path": [
      "d2_60",
      "l60_cp2_16",
      "d2_60"
    ],
    "Cost": 840.48,
    "Data": {
      "total_dh_dist": 6.6,
      "total_dh_time": 19.799999999999997,
      "total_travel_dist": 19.0,
      "total_travel_time": 68.0,
      "total_wait_time": 0,
      "final_time": "2025-09-07 09:10:48",
      "total_charging_time": 0
    }
  },
  "Route_117": {
    "Path": [
      "d1_59",
      "l59_cp1_17",
      "l59_cp2_24",
      "d1_59"
    ],
    "Cost": 834.5,
    "Data": {
      "total_dh_dist": 0.0,
      "total_dh_time": 0.0,
      "total_travel_dist": 22.8,
      "total_travel_time": 81.0,
      "total_wait_time": 7.0,
      "final_time": "2025-09-07 09:14:00",
      "total_charging_time": 0
    }
  },
  "Route_118": {
    "Path": [
      "d2_4",
      "l60_cp1_25",
      "l4_cp1_99",
      "l4_cp2_120",
      "l4_cp1_143",
      "c2_4",
      "l4_cp2_214",
      "l4_cp1_239",
      "l4_cp2_258",
      "l4_cp1_275",
      "l4_cp2_290",
      "d2_4"
    ],
    "Cost": 1965.3205950789813,
    "Data": {
      "total_dh_dist": 54.14116609562109,
      "total_dh_time": 162.42349828686326,
      "total_travel_dist": 211.0,
      "total_travel_time": 592.0,
      "total_wait_time": 209.4965017091689,
      "final_time": "2025-09-08 00:55:24",
      "total_charging_time": 176.2922191091689
    }
  },
  "Route_119": {
    "Path": [
      "d1_59",
      "l59_cp1_33",
      "l4_cp2_92",
      "l4_cp1_115",
      "l4_cp2_138",
      "l4_cp1_163",
      "d1_59"
    ],
    "Cost": 1311.2454605136481,
    "Data": {
      "total_dh_dist": 20.397577969857284,
      "total_dh_time": 61.19273390957185,
      "total_travel_dist": 107.4,
      "total_travel_time": 310.0,
      "total_wait_time": 24.767266083333332,
      "final_time": "2025-09-07 16:35:57.600000",
      "total_charging_time": 0
    }
  },
  "Route_120": {
    "Path": [
      "d1_4",
      "l4_cp1_95",
      "l4_cp2_118",
      "l4_cp1_141",
      "l4_cp2_166",
      "l59_cp1_69",
      "c2_59",
      "l4_cp1_261",
      "l4_cp2_280",
      "d1_4"
    ],
    "Cost": 1539.4670974020712,
    "Data": {
      "total_dh_dist": 12.972122150778691,
      "total_dh_time": 38.91636645233608,
      "total_travel_dist": 155.4,
      "total_travel_time": 438.0,
      "total_wait_time": 236.0836335308491,
      "final_time": "2025-09-07 22:50:00",
      "total_charging_time": 176.93947484751578
    }
  },
  "Route_121": {
    "Path": [
      "d1_59",
      "l59_cp1_41",
      "l4_cp2_116",
      "l4_cp1_137",
      "l4_cp2_164",
      "l4_cp1_181",
      "c2_4",
      "l4_cp2_252",
      "l4_cp1_271",
      "l4_cp2_286",
      "d1_59"
    ],
    "Cost": 1584.564745370315,
    "Data": {
      "total_dh_dist": 8.157577969857282,
      "total_dh_time": 24.47273390957185,
      "total_travel_dist": 179.4,
      "total_travel_time": 490.0,
      "total_wait_time": 204.76726608297736,
      "final_time": "2025-09-07 23:24:14.400000",
      "total_charging_time": 167.04102163297736
    }
  },
  "Route_122": {
    "Path": [
      "d1_4",
      "l4_cp1_109",
      "l4_cp2_132",
      "l4_cp1_153",
      "l4_cp2_174",
      "d1_4"
    ],
    "Cost": 1149.0,
    "Data": {
      "total_dh_dist": 0.0,
      "total_dh_time": 0.0,
      "total_travel_dist": 96.0,
      "total_travel_time": 278.0,
      "total_wait_time": 6.0,
      "final_time": "2025-09-07 16:31:00",
      "total_charging_time": 0
    }
  },
  "Route_123": {
    "Path": [
      "d1_59",
      "l59_cp1_45",
      "l59_cp2_48",
      "l4_cp1_149",
      "l4_cp2_172",
      "l59_cp1_71",
      "c2_59",
      "l60_cp2_110",
      "l4_cp2_288",
      "d1_59"
    ],
    "Cost": 1531.0826100661127,
    "Data": {
      "total_dh_dist": 44.3799536550929,
      "total_dh_time": 133.1398609652787,
      "total_travel_dist": 125.2,
      "total_travel_time": 343.0,
      "total_wait_time": 202.1001390116982,
      "final_time": "2025-09-07 23:31:14.400000",
      "total_charging_time": 153.15894969503154
    }
  },
  "Route_124": {
    "Path": [
      "d1_4",
      "l4_cp1_125",
      "l4_cp2_146",
      "l59_cp2_60",
      "d1_4"
    ],
    "Cost": 1010.0673310267662,
    "Data": {
      "total_dh_dist": 7.629381863909613,
      "total_dh_time": 22.888145591728836,
      "total_travel_dist": 59.4,
      "total_travel_time": 169.0,
      "total_wait_time": 4.351854400000001,
      "final_time": "2025-09-07 15:54:14.400000",
      "total_charging_time": 0
    }
  },
  "Route_125": {
    "Path": [
      "d2_4",
      "l4_cp2_128",
      "l4_cp1_151",
      "d2_4"
    ],
    "Cost": 918.8,
    "Data": {
      "total_dh_dist": 0.0,
      "total_dh_time": 0.0,
      "total_travel_dist": 48.0,
      "total_travel_time": 135.0,
      "total_wait_time": 4.0,
      "final_time": "2025-09-07 15:07:00",
      "total_charging_time": 0
    }
  },
  "Route_126": {
    "Path": [
      "d1_4",
      "l4_cp1_129",
      "l4_cp2_150",
      "l4_cp1_173",
      "d1_4"
    ],
    "Cost": 1178.04,
    "Data": {
      "total_dh_dist": 28.8,
      "total_dh_time": 86.39999999999999,
      "total_travel_dist": 72.0,
      "total_travel_time": 208.0,
      "total_wait_time": 10.0,
      "final_time": "2025-09-07 17:54:24",
      "total_charging_time": 0
    }
  },
  "Route_127": {
    "Path": [
      "d2_4",
      "l60_cp1_51",
      "l60_cp2_58",
      "l59_cp1_57",
      "l4_cp1_179",
      "l59_cp2_72",
      "c1_59",
      "l60_cp1_111",
      "l59_cp2_100",
      "d2_4"
    ],
    "Cost": 1501.57471703404,
    "Data": {
      "total_dh_dist": 45.982458215424984,
      "total_dh_time": 137.94737464627497,
      "total_travel_dist": 115.20000000000002,
      "total_travel_time": 321.0,
      "total_wait_time": 210.09262534067636,
      "final_time": "2025-09-07 23:13:31.200000",
      "total_charging_time": 164.00845734067633
    }
  },
  "Route_128": {
    "Path": [
      "d2_4",
      "l4_cp2_134",
      "l4_cp1_155",
      "l59_cp2_64",
      "l60_cp2_80",
      "d2_4"
    ],
    "Cost": 1261.3911584231137,
    "Data": {
      "total_dh_dist": 37.639688307593126,
      "total_dh_time": 112.91906492277937,
      "total_travel_dist": 78.4,
      "total_travel_time": 232.0,
      "total_wait_time": 13.600935066666668,
      "final_time": "2025-09-07 19:04:31.200000",
      "total_charging_time": 0
    }
  },
  "Route_129": {
    "Path": [
      "d2_4",
      "l4_cp2_136",
      "l4_cp1_161",
      "d2_4"
    ],
    "Cost": 923.6,
    "Data": {
      "total_dh_dist": 0.0,
      "total_dh_time": 0.0,
      "total_travel_dist": 48.0,
      "total_travel_time": 138.0,
      "total_wait_time": 4.0,
      "final_time": "2025-09-07 15:41:00",
      "total_charging_time": 0
    }
  },
  "Route_130": {
    "Path": [
      "d1_4",
      "l60_cp2_54",
      "d1_4"
    ],
    "Cost": 818.336,
    "Data": {
      "total_dh_dist": 7.32,
      "total_dh_time": 21.96,
      "total_travel_dist": 19.0,
      "total_travel_time": 52.0,
      "total_wait_time": 0,
      "final_time": "2025-09-07 14:25:14.400000",
      "total_charging_time": 0
    }
  },
  "Route_131": {
    "Path": [
      "d2_4",
      "l4_cp2_140",
      "l59_cp1_61",
      "d2_4"
    ],
    "Cost": 938.1133987703049,
    "Data": {
      "total_dh_dist": 15.06274028686908,
      "total_dh_time": 45.18822086060723,
      "total_travel_dist": 35.4,
      "total_travel_time": 102.0,
      "total_wait_time": 3.731779133333333,
      "final_time": "2025-09-07 16:00:55.200000",
      "total_charging_time": 0
    }
  },
  "Route_132": {
    "Path": [
      "d2_4",
      "l59_cp2_54",
      "d2_4"
    ],
    "Cost": 852.704,
    "Data": {
      "total_dh_dist": 21.48,
      "total_dh_time": 64.44,
      "total_travel_dist": 11.4,
      "total_travel_time": 31.0,
      "total_wait_time": 0,
      "final_time": "2025-09-07 15:11:31.200000",
      "total_charging_time": 0
    }
  },
  "Route_133": {
    "Path": [
      "d1_4",
      "l60_cp2_60",
      "l60_cp1_65",
      "d1_4"
    ],
    "Cost": 904.604,
    "Data": {
      "total_dh_dist": 6.48,
      "total_dh_time": 19.44,
      "total_travel_dist": 38.0,
      "total_travel_time": 108.0,
      "total_wait_time": 1.0,
      "final_time": "2025-09-07 16:00:43.200000",
      "total_charging_time": 0
    }
  },
  "Route_134": {
    "Path": [
      "d1_4",
      "l60_cp2_84",
      "d1_4"
    ],
    "Cost": 831.136,
    "Data": {
      "total_dh_dist": 7.32,
      "total_dh_time": 21.96,
      "total_travel_dist": 19.0,
      "total_travel_time": 60.0,
      "total_wait_time": 0,
      "final_time": "2025-09-07 18:49:14.400000",
      "total_charging_time": 0
    }
  },
  "Route_135": {
    "Path": [
      "d1_4",
      "l4_cp1_215",
      "l60_cp2_96",
      "l60_cp1_107",
      "l4_cp2_274",
      "l4_cp1_289",
      "d1_4"
    ],
    "Cost": 1354.721353697009,
    "Data": {
      "total_dh_dist": 35.27457544382131,
      "total_dh_time": 105.82372633146392,
      "total_travel_dist": 110.0,
      "total_travel_time": 297.0,
      "total_wait_time": 14.576273666666665,
      "final_time": "2025-09-08 00:49:24",
      "total_charging_time": 0
    }
  },
  "Route_136": {
    "Path": [
      "d1_4",
      "l4_cp1_251",
      "l4_cp2_270",
      "l4_cp1_285",
      "d1_4"
    ],
    "Cost": 1140.04,
    "Data": {
      "total_dh_dist": 28.8,
      "total_dh_time": 86.39999999999999,
      "total_travel_dist": 72.0,
      "total_travel_time": 186.0,
      "total_wait_time": 6.0,
      "final_time": "2025-09-08 00:34:24",
      "total_charging_time": 0
    }
  },
  "Route_137": {
    "Path": [
      "d2_4",
      "l60_cp1_101",
      "d2_4"
    ],
    "Cost": 974.624,
    "Data": {
      "total_dh_dist": 38.879999999999995,
      "total_dh_time": 116.63999999999999,
      "total_travel_dist": 19.0,
      "total_travel_time": 55.0,
      "total_wait_time": 0,
      "final_time": "2025-09-07 22:02:07.200000",
      "total_charging_time": 0
    }
  },
  "Route_138": {
    "Path": [
      "d1_4",
      "l60_cp2_112",
      "l60_cp1_119",
      "d1_4"
    ],
    "Cost": 886.604,
    "Data": {
      "total_dh_dist": 6.48,
      "total_dh_time": 19.44,
      "total_travel_dist": 38.0,
      "total_travel_time": 95.0,
      "total_wait_time": 5.0,
      "final_time": "2025-09-07 22:36:43.200000",
      "total_charging_time": 0
    }
  },
  "Route_139": {
    "Path": [
      "d1_59",
      "l60_cp1_45",
      "l59_cp2_56",
      "l59_cp1_65",
      "l60_cp1_81",
      "l60_cp1_105",
      "d1_59"
    ],
    "Cost": 1387.0569205807337,
    "Data": {
      "total_dh_dist": 36.76182243730875,
      "total_dh_time": 110.28546731192625,
      "total_travel_dist": 79.8,
      "total_travel_time": 230.0,
      "total_wait_time": 203.71453268807386,
      "final_time": "2025-09-07 21:03:00",
      "total_charge_time": 0.0
    }
  },
  "Route_140": {
    "Path": [
      "d1_59",
      "l60_cp1_7",
      "d1_59"
    ],
    "Cost": 808.8,
    "Data": {
      "total_dh_dist": 0.0,
      "total_dh_time": 0.0,
      "total_travel_dist": 19.0,
      "total_travel_time": 68.0,
      "total_wait_time": 0.0,
      "final_time": "2025-09-07 08:11:00",
      "total_charge_time": 0.0
    }
  },
  "Route_141": {
    "Path": [
      "d2_60",
      "l60_cp2_2",
      "l60_cp1_11",
      "l4_cp1_59",
      "d2_60"
    ],
    "Cost": 1111.805148458177,
    "Data": {
      "total_dh_dist": 9.50116609562109,
      "total_dh_time": 28.50349828686327,
      "total_travel_dist": 62.0,
      "total_travel_time": 215.0,
      "total_wait_time": 9.496501713136695,
      "final_time": "2025-09-07 10:20:00",
      "total_charge_time": 0.0
    }
  },
  "Route_142": {
    "Path": [
      "d2_59",
      "l59_cp2_18",
      "d2_59"
    ],
    "Cost": 765.6,
    "Data": {
      "total_dh_dist": 0.0,
      "total_dh_time": 0.0,
      "total_travel_dist": 11.4,
      "total_travel_time": 41.0,
      "total_wait_time": 0.0,
      "final_time": "2025-09-07 08:35:00",
      "total_charge_time": 0.0
    }
  },
  "Route_143": {
    "Path": [
      "d2_59",
      "l59_cp2_38",
      "l59_cp1_47",
      "l59_cp2_58",
      "l59_cp1_67",
      "l59_cp2_74",
      "l59_cp2_80",
      "l59_cp1_85",
      "l4_cp2_268",
      "d2_59"
    ],
    "Cost": 1495.4614605186148,
    "Data": {
      "total_dh_dist": 15.477577969857283,
      "total_dh_time": 46.43273390957185,
      "total_travel_dist": 103.80000000000001,
      "total_travel_time": 294.0,
      "total_wait_time": 319.5672660904281,
      "final_time": "2025-09-07 22:02:00",
      "total_charge_time": 0.0
    }
  },
  "Route_144": {
    "Path": [
      "d1_59",
      "l60_cp1_11",
      "l59_cp2_30",
      "l60_cp1_33",
      "l60_cp2_44",
      "l59_cp1_49",
      "l4_cp1_145",
      "d1_59"
    ],
    "Cost": 1343.491176663033,
    "Data": {
      "total_dh_dist": 10.2248802455677,
      "total_dh_time": 30.6746407367031,
      "total_travel_dist": 103.80000000000001,
      "total_travel_time": 311.0,
      "total_wait_time": 110.32535926329695,
      "final_time": "2025-09-07 14:52:00",
      "total_charge_time": 0.0
    }
  },
  "Route_145": {
    "Path": [
      "d1_4",
      "l4_cp1_23",
      "d1_4"
    ],
    "Cost": 837.6,
    "Data": {
      "total_dh_dist": 0.0,
      "total_dh_time": 0.0,
      "total_travel_dist": 24.0,
      "total_travel_time": 86.0,
      "total_wait_time": 0.0,
      "final_time": "2025-09-07 08:26:00",
      "total_charge_time": 0.0
    }
  },
  "Route_146": {
    "Path": [
      "d2_4",
      "l4_cp2_24",
      "l4_cp1_49",
      "l59_cp2_44",
      "l60_cp1_61",
      "c1_59",
      "l60_cp2_88",
      "l60_cp1_97",
      "l4_cp2_262",
      "l4_cp1_283",
      "d2_4"
    ],
    "Cost": 1945.1574222246895,
    "Data": {
      "total_dh_dist": 20.514865691767938,
      "total_dh_time": 61.544597075303805,
      "total_travel_dist": 164.4,
      "total_travel_time": 494.0,
      "total_wait_time": 261.49438129171904,
      "final_time": "2025-09-07 22:58:00",
      "total_charge_time": 138.96102163297735
    }
  },
  "Route_147": {
    "Path": [
      "d2_60",
      "l60_cp1_29",
      "l4_cp2_106",
      "l60_cp1_63",
      "l60_cp2_68",
      "c1_59",
      "l60_cp2_102",
      "l59_cp1_97",
      "l4_cp1_283",
      "d2_60"
    ],
    "Cost": 1620.8334560706737,
    "Data": {
      "total_dh_dist": 29.40940987268935,
      "total_dh_time": 88.22822961806803,
      "total_travel_dist": 135.4,
      "total_travel_time": 376.0,
      "total_wait_time": 182.16612668823564,
      "final_time": "2025-09-07 22:58:00",
      "total_charge_time": 156.40564369369636
    }
  },
  "Route_148": {
    "Path": [
      "d1_4",
      "l60_cp1_47",
      "l60_cp2_56",
      "l60_cp1_77",
      "l59_cp2_82",
      "l59_cp1_87",
      "l4_cp1_273",
      "d1_4"
    ],
    "Cost": 1434.591176663033,
    "Data": {
      "total_dh_dist": 14.304880245567698,
      "total_dh_time": 42.914640736703106,
      "total_travel_dist": 103.80000000000001,
      "total_travel_time": 287.0,
      "total_wait_time": 295.32535926329706,
      "final_time": "2025-09-07 22:19:00",
      "total_charge_time": 0.0
    }
  },
  "Route_149": {
    "Path": [
      "d1_59",
      "l4_cp1_11",
      "l4_cp2_72",
      "l4_cp1_97",
      "c2_4",
      "l4_cp2_162",
      "l59_cp2_74",
      "l59_cp1_77",
      "l4_cp2_232",
      "l4_cp1_255",
      "l59_cp2_98",
      "d1_59"
    ],
    "Cost": 1915.8708920697854,
    "Data": {
      "total_dh_dist": 15.784537803624179,
      "total_dh_time": 47.35361341087253,
      "total_travel_dist": 178.20000000000002,
      "total_travel_time": 538.0,
      "total_wait_time": 255.2015865891275,
      "final_time": "2025-09-07 22:07:00",
      "total_charge_time": 118.6848
    }
  },
  "Route_150": {
    "Path": [
      "d2_4",
      "l4_cp2_6",
      "l59_cp2_16",
      "l60_cp1_31",
      "l60_cp2_40",
      "l59_cp1_59",
      "l59_cp2_74",
      "c1_59",
      "l4_cp1_265",
      "d2_4"
    ],
    "Cost": 1783.7130060371667,
    "Data": {
      "total_dh_dist": 7.629381863909613,
      "total_dh_time": 22.888145591728836,
      "total_travel_dist": 120.20000000000002,
      "total_travel_time": 367.0,
      "total_wait_time": 409.5028187005722,
      "final_time": "2025-09-07 21:58:00",
      "total_charge_time": 155.609035707699
    }
  },
  "Route_151": {
    "Path": [
      "d1_4",
      "l59_cp2_2",
      "l59_cp1_15",
      "l4_cp2_52",
      "l60_cp1_35",
      "d1_4"
    ],
    "Cost": 1250.5828592931612,
    "Data": {
      "total_dh_dist": 28.26031825672636,
      "total_dh_time": 84.78095477017908,
      "total_travel_dist": 65.8,
      "total_travel_time": 218.0,
      "total_wait_time": 66.49904522982092,
      "final_time": "2025-09-07 11:28:00",
      "total_charge_time": 0.0
    }
  },
  "Route_152": {
    "Path": [
      "d1_59",
      "l59_cp2_48",
      "l60_cp1_83",
      "l60_cp1_103",
      "l60_cp2_114",
      "d1_59"
    ],
    "Cost": 1389.844,
    "Data": {
      "total_dh_dist": 32.68,
      "total_dh_time": 98.03999999999999,
      "total_travel_dist": 68.4,
      "total_travel_time": 186.0,
      "total_wait_time": 291.0,
      "final_time": "2025-09-07 21:47:00",
      "total_charge_time": 0.0
    }
  },
  "Route_153": {
    "Path": [
      "d2_4",
      "l4_cp2_14",
      "l4_cp1_41",
      "l59_cp2_36",
      "l60_cp1_39",
      "l4_cp2_130",
      "d2_4"
    ],
    "Cost": 1324.1501373677734,
    "Data": {
      "total_dh_dist": 7.314865691767938,
      "total_dh_time": 21.94459707530381,
      "total_travel_dist": 102.4,
      "total_travel_time": 320.0,
      "total_wait_time": 110.05540292469618,
      "final_time": "2025-09-07 14:00:00",
      "total_charge_time": 0.0
    }
  },
  "Route_154": {
    "Path": [
      "d2_60",
      "l60_cp2_4",
      "l60_cp1_13",
      "l60_cp2_20",
      "d2_60"
    ],
    "Cost": 1021.7,
    "Data": {
      "total_dh_dist": 0.0,
      "total_dh_time": 0.0,
      "total_travel_dist": 57.0,
      "total_travel_time": 198.0,
      "total_wait_time": 7.0,
      "final_time": "2025-09-07 09:48:00",
      "total_charge_time": 0.0
    }
  },
  "Route_155": {
    "Path": [
      "d1_59",
      "l59_cp1_1",
      "l59_cp2_10",
      "l59_cp1_19",
      "l59_cp2_26",
      "l59_cp1_31",
      "d1_59"
    ],
    "Cost": 1049.8,
    "Data": {
      "total_dh_dist": 0.0,
      "total_dh_time": 0.0,
      "total_travel_dist": 57.0,
      "total_travel_time": 195.0,
      "total_wait_time": 54.0,
      "final_time": "2025-09-07 10:09:00",
      "total_charge_time": 0.0
    }
  },
  "Route_156": {
    "Path": [
      "d1_59",
      "l60_cp1_23",
      "l60_cp2_64",
      "l60_cp1_69",
      "l60_cp2_74",
      "l59_cp1_79",
      "l60_cp1_99",
      "d1_59"
    ],
    "Cost": 1498.1330749502567,
    "Data": {
      "total_dh_dist": 11.086324055650667,
      "total_dh_time": 33.258972166952,
      "total_travel_dist": 106.4,
      "total_travel_time": 320.0,
      "total_wait_time": 332.74102783304807,
      "final_time": "2025-09-07 20:36:00",
      "total_charge_time": 0.0
    }
  },
  "Route_157": {
    "Path": [
      "d1_4",
      "l4_cp1_11",
      "l59_cp2_50",
      "l60_cp1_55",
      "l59_cp2_78",
      "l59_cp1_87",
      "l59_cp2_94",
      "l59_cp1_99",
      "d1_4"
    ],
    "Cost": 1671.9173061490915,
    "Data": {
      "total_dh_dist": 10.75307635151537,
      "total_dh_time": 32.25922905454611,
      "total_travel_dist": 100.00000000000001,
      "total_travel_time": 287.0,
      "total_wait_time": 630.740770945454,
      "final_time": "2025-09-07 22:10:00",
      "total_charge_time": 0.0
    }
  },
  "Route_158": {
    "Path": [
      "d1_4",
      "l4_cp1_21",
      "l4_cp2_48",
      "l59_cp1_43",
      "l59_cp1_53",
      "l59_cp2_62",
      "c1_4",
      "l60_cp2_94",
      "l59_cp1_89",
      "l4_cp1_277",
      "d1_4"
    ],
    "Cost": 1729.1125374138414,
    "Data": {
      "total_dh_dist": 31.69212215077869,
      "total_dh_time": 95.07636645233607,
      "total_travel_dist": 136.60000000000002,
      "total_travel_time": 406.0,
      "total_wait_time": 274.8433587001482,
      "final_time": "2025-09-07 22:38:00",
      "total_charge_time": 167.08027484751577
    }
  },
  "Route_159": {
    "Path": [
      "d2_60",
      "l60_cp2_10",
      "l59_cp1_25",
      "l60_cp2_28",
      "l60_cp1_37",
      "l60_cp2_48",
      "d2_60"
    ],
    "Cost": 1209.8238456304769,
    "Data": {
      "total_dh_dist": 6.675498381658087,
      "total_dh_time": 20.026495144974263,
      "total_travel_dist": 87.4,
      "total_travel_time": 275.0,
      "total_wait_time": 53.973504855025794,
      "final_time": "2025-09-07 13:04:00",
      "total_charge_time": 0.0
    }
  }
}